flask_cloudy.py
Flask_Cloudy-1.1.0.dist-info/METADATA
Flask_Cloudy-1.1.0.dist-info/RECORD
Flask_Cloudy-1.1.0.dist-info/WHEEL
Flask_Cloudy-1.1.0.dist-info/top_level.txt
example/__init__.py
example/app.py
tests/__init__.py
tests/config.py
tests/test_cloudy.py
